raidx-0.1.1.dist-info/METADATA
raidx-0.1.1.dist-info/WHEEL
raidx-0.1.1.dist-info/licenses/LICENSE
raidx/__init__.py
raidx/raidx.cpython-38-i386-linux-gnu.so
raidx-0.1.1.dist-info/RECORD
