Metadata-Version: 2.4
Name: raidx
Version: 0.1.1
Classifier: Programming Language :: Rust
Classifier: Programming Language :: Python :: Implementation :: CPython
Classifier: Programming Language :: Python :: Implementation :: PyPy
Requires-Dist: pytest-benchmark>=4.0.0 ; extra == 'benchmark'
Requires-Dist: pyfaidx>=0.6.0 ; extra == 'benchmark'
Requires-Dist: click>=8.0.0 ; extra == 'benchmark'
Requires-Dist: tabulate>=0.9.0 ; extra == 'benchmark'
Requires-Dist: pytest>=7.0.0 ; extra == 'dev'
Requires-Dist: pytest-benchmark>=4.0.0 ; extra == 'dev'
Requires-Dist: pyfaidx>=0.6.0 ; extra == 'dev'
Requires-Dist: click>=8.0.0 ; extra == 'dev'
Requires-Dist: tabulate>=0.9.0 ; extra == 'dev'
Provides-Extra: benchmark
Provides-Extra: dev
License-File: LICENSE
Requires-Python: >=3.8
